{
  "updated_at": "2026-07-14T20:47",
  "stats": {
    "total_articles": 13810,
    "analyzed": 30,
    "digests": 1,
    "by_source": {
      "ТАСС": 20,
      "РИА Новости": 20,
      "Интерфакс": 20,
      "The Guardian World": 20,
      "BBC World": 20,
      "NYT World": 20,
      "NPR World": 10,
      "Al Jazeera": 20,
      "France24": 20,
      "DW (Германия)": 20,
      "Times of India": 20,
      "AllAfrica": 20,
      "GDELT: Россия/СНГ (rus)": 20,
      "GDELT: Китай (zho)": 0,
      "GDELT: Латинская Америка (spa)": 20,
      "GDELT: Ближний Восток (ara)": 0,
      "GDELT Cloud: Европа": 0,
      "GDELT Cloud: Азия": 0,
      "GDELT Cloud: Ближний Восток": 0,
      "GDELT Cloud: Африка": 0,
      "GDELT Cloud: Северная Америка": 0
    }
  },
  "analysis": {
    "text": "Вот аналитический обзор новостного дайджеста, составленный по заданной структуре.\n\n### 1. КЛЮЧЕВЫЕ СОБЫТИЯ\n\n**Массированная угроза БПЛА в Центральной России**\n- **Беспилотная опасность** объявлена в шести регионах: Волгоградской, Пензенской, Ярославской, Костромской, Владимирской областях и Мордовии. Это волна предупреждений, охватившая обширную территорию от юга до центра России.\n\n**Паралич региональной авиации**\n- Введены временные ограничения на работу аэропортов **Иваново**, **Ярославля** и **Череповца**. Крупнейший московский хаб **Домодедово** перешел на режим «по согласованию» (фактически — работа с перебоями).\n\n**Эскалация в Харьковской области и контроль МАГАТЭ**\n- В Харьковской области прогремели **взрывы**.\n- МАГАТЭ заявило о мониторинге ситуации, чтобы Киев **не использовал британский уран в военных целях**, что указывает на риск применения «грязной бомбы» или ядерных материалов.\n\n**Рекорды ЧМ-2022 и контракты в НХЛ**\n- **Эрлинг Холанд** (Норвегия) установил достижение, забив 7 голов на дебютном ЧМ — первый случай за 52 года.\n- **Неймар** вошел в элитарный клуб, сравнявшись с Пеле по голам на четырех мундиалях.\n- **Егор Чинахов** подписал трехлетний контракт с «Питтсбург Пингвинз».\n\n**Внутренние социальные и законодательные инициативы**\n- Госдума предложила **освободить от налогов** продажу собранных в лесу грибов и ягод (при определенных условиях).\n- Депутаты также готовят закон об обязательном направлении копий решений по административным делам потерпевшим.\n- **Треть работающих россиян** не брали больничный в течение года (данные аналитиков).\n\n**Международные инциденты и логистика**\n- В Калифорнии (США) после Дня независимости **арестовано более 400 человек**.\n- Австралийский премьер **извинился** за неудачную шутку о певице Кайли Миноуг.\n- **15 из 20 судов с удобрениями** освобождены из-под ареста в Ормузском проливе — сигнал о разрядке в цепочках поставок продовольствия.\n\n### 2. СВЯЗИ МЕЖДУ РЕГИОНАМИ\n\n- **БПЛА и логистический коллапс.** Прямая причинно-следственная связь: объявление беспилотной опасности в **Ярославской, Владимирской, Костромской** областях привело к введению временных ограничений в аэропортах **Иваново, Ярославля и Череповца**. Домодедово, находясь в Московской области, перешел на усиленный режим как реакция на общую угрозу в ЦФО.\n- **Украинский фронт и ядерная безопасность.** Взрывы в **Харьковской области** на фоне заявлений МАГАТЭ о британском уране формируют единый контекст: риск тактического применения радиоактивных материалов в зоне конфликта. Контроль агентства напрямую увязан с эскалацией на востоке Украины.\n- **Глобальный рынок удобрений.** Разблокировка судов в **Ормузском проливе** (Иран/ОАЭ) логически связана с продовольственной безопасностью РФ и мира. На фоне внутренних инициатив (налог на грибы) эта новость показывает контраст: РФ стимулирует сбор дикоросов, а глобальный Юг размораживает поставки химудобрений.\n- **Спорт как зеркало депопуляции?** На фоне позитивных спортивных рекордов (Холанд, Неймар, Чинахов) новость о том, что **треть россиян не ходят на больничный**, может указывать либо на высокую производительность, либо (что вероятнее) на страх потери дохода и дефицит кадров — скрытый кризис на рынке труда.\n\n### 3. ПАТТЕРНЫ И ТРЕНДЫ\n\n- **Пространственный паттерн «кольцо угрозы».** Угроза БПЛА охватила практически все регионы **Верхнего Поволжья** (Ярославская, Костромская, Владимирская, Ивановская) плюс южный фланг (Волгоградская) и Мордовию. Это не точечные инциденты, а **системное давление на транспортную инфраструктуру центральной части РФ**.\n- **Дублирование информации разными источниками.** Заголовки о БПЛА и закрытии аэропортов повторяются у ТАСС, РИА Новости и Интерфакса почти дословно. Это говорит о **высокой степени тревожности** редакций и стремлении максимально быстро продублировать экстренную информацию, а также об отсутствии новых фактов после первого сообщения.\n- **Сезонный и ситуационный тренд в США.** Аресты более 400 человек в Калифорнии после Дня независимости — повторяющийся ежегодный паттерн (массовые задержания после праздничных беспорядков) на фоне общего роста преступности в мегаполисах США.\n- **Сдвиг в трудовой этике.** Данные о том, что треть россиян не берут больничные, коррелируют с трендом на «присутствие любой ценой» (presenteeism). Это может быть следствием ужесточения контроля (закон об административных делах — смежный сигнал) или неформальной занятости.\n\n### 4. НЕОЖИДАННЫЕ ИНСАЙТЫ\n\n- **«Эбола» на фоне БПЛА.** Новость о возможном длительном выявлении вируса Эболы у переболевших (до полугода) резко контрастирует с военно-технической повесткой. Это может быть отложенным инфоповодом, готовящим общественное мнение к возможным **биологическим угрозам** в зоне СВО или тропических регионах, куда перемещается логистика РФ.\n- **Контраст «грибы-ракеты».** Законопроект о безналоговой продаже грибов выглядит почти иронично на фоне закрытых аэропортов и беспилотной опасности. Создается образ двойственности: власть стимулирует население к **«натуральному хозяйству»** и выживанию, одновременно перекрывая транспортные артерии.\n- **«Серп и Молот» как символ.** Отмена остановки поездов МЦД-4 на станции с советской символикой «Серп и Молот» (с 6 июля) случайно совпадает по времени с волной БПЛА. Символическая «пролетка без остановки» мимо коммунистического символа может быть прочитана как метафора **прощания с эпохой безопасности** или военно-административного транзита.\n- **Тишина в небе vs голос в эфире.** Глава Тувы обещает оперативно сообщать о поисках пропавших девочек — это единичная гуманитарная новость на фоне массы «жестких» сообщений. Она обнажает тревожное противоречие: пока одни регионы парализованы дронами, в других ищут детей, и государство гарантирует лишь **информационное сопровождение**, а не физическую защиту.",
    "created_at": "2026-07-14 20:47:31"
  },
  "recent_articles": [
    {
      "source": "ТАСС",
      "title": "Число жертв землетрясения в Венесуэле достигло 4 734",
      "url": "https://tass.ru/proisshestviya/27917389",
      "published_at": "2026-07-14T20:40:25+00:00"
    },
    {
      "source": "РИА Новости",
      "title": "США примут санкции против России до августа, утверждают в сенате",
      "url": "https://ria.ru/20260714/sanktsii-2104873137.html",
      "published_at": "2026-07-14T20:38:48+00:00"
    },
    {
      "source": "РИА Новости",
      "title": "Новый законопроект США вводит санкции против четырех российских банков",
      "url": "https://ria.ru/20260714/zakonoproekt-2104872857.html",
      "published_at": "2026-07-14T20:36:41+00:00"
    },
    {
      "source": "Интерфакс",
      "title": "ВС США приступили к блокаде иранских портов",
      "url": "https://www.interfax.ru/world/1103322",
      "published_at": "2026-07-14T20:35:00+00:00"
    },
    {
      "source": "Интерфакс",
      "title": "Число жертв землетрясений в Венесуэле превысило 4,7 тыс. человек",
      "url": "https://www.interfax.ru/world/1103321",
      "published_at": "2026-07-14T20:33:00+00:00"
    },
    {
      "source": "РИА Новости",
      "title": "США снизят пошлины для пяти крупнейших покупателей российской нефти и газа",
      "url": "https://ria.ru/20260714/ssha-2104872650.html",
      "published_at": "2026-07-14T20:32:33+00:00"
    },
    {
      "source": "РИА Новости",
      "title": "В Литве одобрили план, предусматривающий самостоятельную эвакуацию жителей",
      "url": "https://ria.ru/20260714/litva-2104872505.html",
      "published_at": "2026-07-14T20:30:56+00:00"
    },
    {
      "source": "Times of India",
      "title": "US eases Russia sanctions bill, cuts tariff threat on India and China from 500% to 100%",
      "url": "https://timesofindia.indiatimes.com/business/international-business/us-eases-russia-sanctions-bill-cuts-tariff-threat-on-india-and-china-from-500-to-100/articleshow/132400873.cms",
      "published_at": "2026-07-14T20:29:49+00:00"
    },
    {
      "source": "ТАСС",
      "title": "Росатом от имени правительства РФ подпишет с Индией меморандум о сотрудничестве по СМП",
      "url": "https://tass.ru/ekonomika/27917383",
      "published_at": "2026-07-14T20:29:33+00:00"
    },
    {
      "source": "РИА Новости",
      "title": "США возобновили морскую блокаду Ирана",
      "url": "https://ria.ru/20260714/ssha-2104872346.html",
      "published_at": "2026-07-14T20:28:40+00:00"
    },
    {
      "source": "ТАСС",
      "title": "Reuters: измененный проект санкций США допускает вывод из-под них части партнеров РФ",
      "url": "https://tass.ru/mezhdunarodnaya-panorama/27917377",
      "published_at": "2026-07-14T20:28:32+00:00"
    },
    {
      "source": "ТАСС",
      "title": "В Тульской области сбили девять беспилотников ВСУ",
      "url": "https://tass.ru/proisshestviya/27917381",
      "published_at": "2026-07-14T20:28:18+00:00"
    },
    {
      "source": "РИА Новости",
      "title": "Над Тульской областью уничтожили девять украинских беспилотников",
      "url": "https://ria.ru/20260714/bespilotniki-2104872182.html",
      "published_at": "2026-07-14T20:25:56+00:00"
    },
    {
      "source": "ТАСС",
      "title": "Госдепартамент: давление США на Кубу сейчас сильнее, чем когда-либо",
      "url": "https://tass.ru/mezhdunarodnaya-panorama/27917369",
      "published_at": "2026-07-14T20:19:17+00:00"
    },
    {
      "source": "Al Jazeera",
      "title": "Worker killed in furnace explosion fire at Indian recycling plant",
      "url": "https://www.aljazeera.com/video/newsfeed/2026/7/14/worker-killed-in-furnace-explosion-fire-at-indian-recycling-plant?traffic_source=rss",
      "published_at": "2026-07-14T20:18:36+00:00"
    },
    {
      "source": "Al Jazeera",
      "title": "Why Yemen’s long ‘no war, no peace’ deadlock may be ending",
      "url": "https://www.aljazeera.com/features/2026/7/14/why-yemens-long-no-war-no-peace-deadlock-may-be-ending?traffic_source=rss",
      "published_at": "2026-07-14T20:17:56+00:00"
    },
    {
      "source": "Al Jazeera",
      "title": "Mahmoud Khalil alleges conspiracy in lawsuit against Trump officials",
      "url": "https://www.aljazeera.com/news/2026/7/14/mahmoud-khalil-alleges-conspiracy-in-lawsuit-against-trump-officials?traffic_source=rss",
      "published_at": "2026-07-14T20:16:52+00:00"
    },
    {
      "source": "ТАСС",
      "title": "Тысячи болельщиков следят в фан-зонах Мадрида за матчем против сборной Франции",
      "url": "https://tass.ru/sport/27917373",
      "published_at": "2026-07-14T20:16:35+00:00"
    },
    {
      "source": "РИА Новости",
      "title": "Русский язык должен исчезнуть из СМИ, заявил министр культуры Латвии",
      "url": "https://ria.ru/20260714/latvija-2104871599.html",
      "published_at": "2026-07-14T20:16:31+00:00"
    },
    {
      "source": "France24",
      "title": "Triple murder makes headlines in the UK and South Africa",
      "url": "https://www.france24.com/en/triple-murder-makes-headlines-in-the-uk-and-south-africa",
      "published_at": "2026-07-14T20:15:24+00:00"
    }
  ]
}