{
  "updated_at": "2026-07-21T13:08",
  "stats": {
    "total_articles": 18655,
    "analyzed": 30,
    "digests": 1,
    "by_source": {
      "ТАСС": 20,
      "РИА Новости": 20,
      "Интерфакс": 20,
      "The Guardian World": 20,
      "BBC World": 20,
      "NYT World": 20,
      "NPR World": 10,
      "Al Jazeera": 20,
      "France24": 20,
      "DW (Германия)": 20,
      "Times of India": 20,
      "AllAfrica": 20,
      "GDELT: Россия/СНГ (rus)": 20,
      "GDELT: Китай (zho)": 20,
      "GDELT: Латинская Америка (spa)": 20,
      "GDELT: Ближний Восток (ara)": 0,
      "GDELT Cloud: Европа": 0,
      "GDELT Cloud: Азия": 0,
      "GDELT Cloud: Ближний Восток": 0,
      "GDELT Cloud: Африка": 0,
      "GDELT Cloud: Северная Америка": 0
    }
  },
  "analysis": {
    "text": "Вот аналитический обзор новостного дайджеста, составленный по заданной структуре.\n\n### 1. КЛЮЧЕВЫЕ СОБЫТИЯ\n\n**Массированная угроза БПЛА в Центральной России**\n- **Беспилотная опасность** объявлена в шести регионах: Волгоградской, Пензенской, Ярославской, Костромской, Владимирской областях и Мордовии. Это волна предупреждений, охватившая обширную территорию от юга до центра России.\n\n**Паралич региональной авиации**\n- Введены временные ограничения на работу аэропортов **Иваново**, **Ярославля** и **Череповца**. Крупнейший московский хаб **Домодедово** перешел на режим «по согласованию» (фактически — работа с перебоями).\n\n**Эскалация в Харьковской области и контроль МАГАТЭ**\n- В Харьковской области прогремели **взрывы**.\n- МАГАТЭ заявило о мониторинге ситуации, чтобы Киев **не использовал британский уран в военных целях**, что указывает на риск применения «грязной бомбы» или ядерных материалов.\n\n**Рекорды ЧМ-2022 и контракты в НХЛ**\n- **Эрлинг Холанд** (Норвегия) установил достижение, забив 7 голов на дебютном ЧМ — первый случай за 52 года.\n- **Неймар** вошел в элитарный клуб, сравнявшись с Пеле по голам на четырех мундиалях.\n- **Егор Чинахов** подписал трехлетний контракт с «Питтсбург Пингвинз».\n\n**Внутренние социальные и законодательные инициативы**\n- Госдума предложила **освободить от налогов** продажу собранных в лесу грибов и ягод (при определенных условиях).\n- Депутаты также готовят закон об обязательном направлении копий решений по административным делам потерпевшим.\n- **Треть работающих россиян** не брали больничный в течение года (данные аналитиков).\n\n**Международные инциденты и логистика**\n- В Калифорнии (США) после Дня независимости **арестовано более 400 человек**.\n- Австралийский премьер **извинился** за неудачную шутку о певице Кайли Миноуг.\n- **15 из 20 судов с удобрениями** освобождены из-под ареста в Ормузском проливе — сигнал о разрядке в цепочках поставок продовольствия.\n\n### 2. СВЯЗИ МЕЖДУ РЕГИОНАМИ\n\n- **БПЛА и логистический коллапс.** Прямая причинно-следственная связь: объявление беспилотной опасности в **Ярославской, Владимирской, Костромской** областях привело к введению временных ограничений в аэропортах **Иваново, Ярославля и Череповца**. Домодедово, находясь в Московской области, перешел на усиленный режим как реакция на общую угрозу в ЦФО.\n- **Украинский фронт и ядерная безопасность.** Взрывы в **Харьковской области** на фоне заявлений МАГАТЭ о британском уране формируют единый контекст: риск тактического применения радиоактивных материалов в зоне конфликта. Контроль агентства напрямую увязан с эскалацией на востоке Украины.\n- **Глобальный рынок удобрений.** Разблокировка судов в **Ормузском проливе** (Иран/ОАЭ) логически связана с продовольственной безопасностью РФ и мира. На фоне внутренних инициатив (налог на грибы) эта новость показывает контраст: РФ стимулирует сбор дикоросов, а глобальный Юг размораживает поставки химудобрений.\n- **Спорт как зеркало депопуляции?** На фоне позитивных спортивных рекордов (Холанд, Неймар, Чинахов) новость о том, что **треть россиян не ходят на больничный**, может указывать либо на высокую производительность, либо (что вероятнее) на страх потери дохода и дефицит кадров — скрытый кризис на рынке труда.\n\n### 3. ПАТТЕРНЫ И ТРЕНДЫ\n\n- **Пространственный паттерн «кольцо угрозы».** Угроза БПЛА охватила практически все регионы **Верхнего Поволжья** (Ярославская, Костромская, Владимирская, Ивановская) плюс южный фланг (Волгоградская) и Мордовию. Это не точечные инциденты, а **системное давление на транспортную инфраструктуру центральной части РФ**.\n- **Дублирование информации разными источниками.** Заголовки о БПЛА и закрытии аэропортов повторяются у ТАСС, РИА Новости и Интерфакса почти дословно. Это говорит о **высокой степени тревожности** редакций и стремлении максимально быстро продублировать экстренную информацию, а также об отсутствии новых фактов после первого сообщения.\n- **Сезонный и ситуационный тренд в США.** Аресты более 400 человек в Калифорнии после Дня независимости — повторяющийся ежегодный паттерн (массовые задержания после праздничных беспорядков) на фоне общего роста преступности в мегаполисах США.\n- **Сдвиг в трудовой этике.** Данные о том, что треть россиян не берут больничные, коррелируют с трендом на «присутствие любой ценой» (presenteeism). Это может быть следствием ужесточения контроля (закон об административных делах — смежный сигнал) или неформальной занятости.\n\n### 4. НЕОЖИДАННЫЕ ИНСАЙТЫ\n\n- **«Эбола» на фоне БПЛА.** Новость о возможном длительном выявлении вируса Эболы у переболевших (до полугода) резко контрастирует с военно-технической повесткой. Это может быть отложенным инфоповодом, готовящим общественное мнение к возможным **биологическим угрозам** в зоне СВО или тропических регионах, куда перемещается логистика РФ.\n- **Контраст «грибы-ракеты».** Законопроект о безналоговой продаже грибов выглядит почти иронично на фоне закрытых аэропортов и беспилотной опасности. Создается образ двойственности: власть стимулирует население к **«натуральному хозяйству»** и выживанию, одновременно перекрывая транспортные артерии.\n- **«Серп и Молот» как символ.** Отмена остановки поездов МЦД-4 на станции с советской символикой «Серп и Молот» (с 6 июля) случайно совпадает по времени с волной БПЛА. Символическая «пролетка без остановки» мимо коммунистического символа может быть прочитана как метафора **прощания с эпохой безопасности** или военно-административного транзита.\n- **Тишина в небе vs голос в эфире.** Глава Тувы обещает оперативно сообщать о поисках пропавших девочек — это единичная гуманитарная новость на фоне массы «жестких» сообщений. Она обнажает тревожное противоречие: пока одни регионы парализованы дронами, в других ищут детей, и государство гарантирует лишь **информационное сопровождение**, а не физическую защиту.",
    "created_at": "2026-07-21 13:08:16"
  },
  "recent_articles": [
    {
      "source": "РИА Новости",
      "title": "Глава Балашихи подал документы для выдвижения кандидатом в депутаты Госдумы",
      "url": "https://ria.ru/20260721/glava-2106063090.html",
      "published_at": "2026-07-21T13:03:49+00:00"
    },
    {
      "source": "РИА Новости",
      "title": "На Украине учительницу оштрафовали из-за мультфильма на русском языке",
      "url": "https://ria.ru/20260721/ukraina-2106062903.html",
      "published_at": "2026-07-21T13:03:06+00:00"
    },
    {
      "source": "РИА Новости",
      "title": "ГД упростила переезд компаний в \"русские офшоры\" при блокировке за рубежом",
      "url": "https://ria.ru/20260721/gosduma-2106062522.html",
      "published_at": "2026-07-21T13:01:48+00:00"
    },
    {
      "source": "ТАСС",
      "title": "Житель Константиновки через Starlink на \"Бабе-Яге\" связался с ВС РФ для эвакуации",
      "url": "https://tass.ru/armiya-i-opk/27937691",
      "published_at": "2026-07-21T13:01:20+00:00"
    },
    {
      "source": "РИА Новости",
      "title": "Алиев и Мерц подписали декларацию о двустороннем партнерстве стран",
      "url": "https://ria.ru/20260721/aliev-2106062208.html",
      "published_at": "2026-07-21T13:01:14+00:00"
    },
    {
      "source": "РИА Новости",
      "title": "В Энергодаре простились с убитым главным инженером ЗАЭС Яковлевым",
      "url": "https://ria.ru/20260721/energodar-2106062375.html",
      "published_at": "2026-07-21T13:01:14+00:00"
    },
    {
      "source": "ТАСС",
      "title": "ЕК приняла окончательное решение о лишении Венецианской биеннале €2 млн",
      "url": "https://tass.ru/mezhdunarodnaya-panorama/27937729",
      "published_at": "2026-07-21T13:00:40+00:00"
    },
    {
      "source": "РИА Новости",
      "title": "Гастроэнтеролог предупредила об опасности частого употребления кофе",
      "url": "https://ria.ru/20260721/kofe-2106062037.html",
      "published_at": "2026-07-21T12:59:07+00:00"
    },
    {
      "source": "ТАСС",
      "title": "В шведской крепости XVII века на Охтинском мысу нашли кошелек солдата",
      "url": "https://tass.ru/nauka/27936023",
      "published_at": "2026-07-21T12:59:03+00:00"
    },
    {
      "source": "Интерфакс",
      "title": "\"СовЭкон\" снизил прогноз сбора пшеницы в России в 2026 году",
      "url": "https://www.interfax.ru/business/1104609",
      "published_at": "2026-07-21T12:59:00+00:00"
    },
    {
      "source": "France24",
      "title": "Fake images circulate of Spanish World Cup players draped in Palestinian flags",
      "url": "https://www.france24.com/en/sport/20260721-fake-images-circulate-spanish-world-cup-players-draped-palestinian-flags",
      "published_at": "2026-07-21T12:58:46+00:00"
    },
    {
      "source": "ТАСС",
      "title": "Новым председателем правления \"WB банка\" назначили Святослава Емельянова",
      "url": "https://tass.ru/ekonomika/27937719",
      "published_at": "2026-07-21T12:58:10+00:00"
    },
    {
      "source": "РИА Новости",
      "title": "Врачи рассказали о состоянии пострадавших при атаках ВСУ белгородцев",
      "url": "https://ria.ru/20260721/postradavshie-2106061485.html",
      "published_at": "2026-07-21T12:57:35+00:00"
    },
    {
      "source": "ТАСС",
      "title": "На ЗАЭС заявили о сложной обстановке в Энергодаре",
      "url": "https://tass.ru/proisshestviya/27937641",
      "published_at": "2026-07-21T12:54:17+00:00"
    },
    {
      "source": "Интерфакс",
      "title": "На бывшем заводе GM в Петербурге запущено производство седана Tenet A8",
      "url": "https://www.interfax.ru/business/1104606",
      "published_at": "2026-07-21T12:54:00+00:00"
    },
    {
      "source": "РИА Новости",
      "title": "Губернатор ЕАО рассказала о возвращении учителей в систему образования",
      "url": "https://ria.ru/20260721/rossiya-2106060943.html",
      "published_at": "2026-07-21T12:53:47+00:00"
    },
    {
      "source": "Интерфакс",
      "title": "Умер художник Владимир Пименов",
      "url": "https://www.interfax.ru/culture/1104607",
      "published_at": "2026-07-21T12:53:00+00:00"
    },
    {
      "source": "The Guardian World",
      "title": "Canada ready to ‘intensify’ trade talks as Trump reportedly prepares to hit more countries with new tariffs – US politics live",
      "url": "https://www.theguardian.com/us-news/live/2026/jul/21/donald-trump-tariffs-canada-mark-carney-lebanon-republicans-gop-spending-bill-latest-news-updates",
      "published_at": "2026-07-21T12:52:21+00:00"
    },
    {
      "source": "ТАСС",
      "title": "Украинские СМИ назвали Умеровова одним из фаворитов на должность посла в США",
      "url": "https://tass.ru/mezhdunarodnaya-panorama/27937679",
      "published_at": "2026-07-21T12:51:32+00:00"
    },
    {
      "source": "ТАСС",
      "title": "Депутат Затулин: Сочи успешно справляется с попытками Киева сорвать турсезон",
      "url": "https://tass.ru/obschestvo/27937623",
      "published_at": "2026-07-21T12:51:27+00:00"
    }
  ]
}